Workbook
Name Slicer_Channel: #N/A
Name Slicer_Region: #N/A
Name Slicer_Sales_Rep: #N/A

Sheet Cleaned sheet
A1: Order ID | B1: Order Date | C1: Customer ID | D1: Sales Rep | E1: Region | F1: Product | G1: Category | H1: Cleaned Category | I1: Channel | J1: Quantity | K1: Unit Price (NGN) | L1: Discount (%) | M1: Status | N1: Column1 | O1: Revenue | P1: Discount Amount | Q1: Net Revenue
A2: ORD-28465 | B2: 45301 | C2: CUST-4872 | D2: Ibrahim Musa | E2: East | F2: SmartPhone X | G2: Electronics | H2: =_xlfn.XLOOKUP(F2,Analysis!A:A,Analysis!B:B,) -> Electronics | I2: In-Store | J2: 14 | K2: 220000 | L2: 0 | M2: Completed | N2: =PROPER(M2) -> Completed | O2: =SUM(Table1[[#This Row],[Quantity]]*Table1[[#This Row],[Unit Price (NGN)]]) -> 3080000 | P2: =SUM(Table1[[#This Row],[Discount (%)]]*Table1[[#This Row],[Revenue]]) -> 0 | Q2: =SUM(Table1[[#This Row],[Revenue]]-Table1[[#This Row],[Discount Amount]]) -> 3080000
A3: ORD-11553 | B3: 45559 | C3: CUST-2125 | D3: Missing Sales Rep | E3: East | F3: Laptop Pro | G3: Electronics | H3: =_xlfn.XLOOKUP(F3,Analysis!A:A,Analysis!B:B,) -> Electronics | I3: Online | J3: 17 | K3: 450000 | L3: 0.2 | M3: Completed | N3: =PROPER(M3) -> Completed | O3: =SUM(Table1[[#This Row],[Quantity]]*Table1[[#This Row],[Unit Price (NGN)]]) -> 7650000 | P3: =SUM(Table1[[#This Row],[Discount (%)]]*Table1[[#This Row],[Revenue]]) -> 1530000 | Q3: =SUM(Table1[[#This Row],[Revenue]]-Table1[[#This Row],[Discount Amount]]) -> 6120000
A4: ORD-71894 | B4: 45522 | C4: CUST-1592 | D4: Ibrahim Musa | E4: South | F4: Wireless Earbuds | G4: Accessories | H4: =_xlfn.XLOOKUP(F4,Analysis!A:A,Analysis!B:B,) -> Accessories | I4: Missing Channel | J4: 17 | K4: 35000 | L4: 0.15 | M4: Completed | N4: =PROPER(M4) -> Completed | O4: =SUM(Table1[[#This Row],[Quantity]]*Table1[[#This Row],[Unit Price (NGN)]]) -> 595000 | P4: =SUM(Table1[[#This Row],[Discount (%)]]*Table1[[#This Row],[Revenue]]) -> 89250 | Q4: =SUM(Table1[[#This Row],[Revenue]]-Table1[[#This Row],[Discount Amount]]) -> 505750
A5: ORD-25389 | B5: 45463 | C5: CUST-1904 | D5: Ngozi Adeyemi | E5: South | F5: Laptop pro | G5: Electronics | H5: =_xlfn.XLOOKUP(F5,Analysis!A:A,Analysis!B:B,) -> Electronics | I5: online | J5: 5 | K5: 450000 | L5: 0.05 | M5: Cancelled | N5: =PROPER(M5) -> Cancelled | O5: =SUM(Table1[[#This Row],[Quantity]]*Table1[[#This Row],[Unit Price (NGN)]]) -> 2250000 | P5: =SUM(Table1[[#This Row],[Discount (%)]]*Table1[[#This Row],[Revenue]]) -> 112500 | Q5: =SUM(Table1[[#This Row],[Revenue]]-Table1[[#This Row],[Discount Amount]]) -> 2137500 | U5: 100
A6: ORD-36111 | B6: 45508 | C6: CUST-1971 | D6: Ibrahim Musa | E6: North | F6: Keyboard Mech | G6: Accessories | H6: =_xlfn.XLOOKUP(F6,Analysis!A:A,Analysis!B:B,) -> Accessories | I6: Distributor | J6: 19 | K6: 28000 | L6: 0 | M6: Returned | N6: =PROPER(M6) -> Returned | O6: =SUM(Table1[[#This Row],[Quantity]]*Table1[[#This Row],[Unit Price (NGN)]]) -> 532000 | P6: =SUM(Table1[[#This Row],[Discount (%)]]*Table1[[#This Row],[Revenue]]) -> 0 | Q6: =SUM(Table1[[#This Row],[Revenue]]-Table1[[#This Row],[Discount Amount]]) -> 532000
A7: ORD-44100 | B7: 45304 | C7: CUST-4500 | D7: Kemi Adebayo | E7: North | F7: Tablet Air | G7: Electronics | H7: =_xlfn.XLOOKUP(F7,Analysis!A:A,Analysis!B:B,) -> Electronics | I7: In-Store | J7: 8 | K7: 180000 | L7: 0 | M7: Completed | N7: =PROPER(M7) -> Completed | O7: =SUM(Table1[[#This Row],[Quantity]]*Table1[[#This Row],[Unit Price (NGN)]]) -> 1440000 | P7: =SUM(Table1[[#This Row],[Discount (%)]]*Table1[[#This Row],[Revenue]]) -> 0 | Q7: =SUM(Table1[[#This Row],[Revenue]]-Table1[[#This Row],[Discount Amount]]) -> 1440000
A8: ORD-45509 | B8: 45420 | C8: CUST-1494 | D8: Ngozi Adeyemi | E8: East | F8: Laptop Pro | G8: Electronics | H8: =_xlfn.XLOOKUP(F8,Analysis!A:A,Analysis!B:B,) -> Electronics | I8: Online | J8: 18 | K8: 450000 | L8: 0.2 | M8: Completed | N8: =PROPER(M8) -> Completed | O8: =SUM(Table1[[#This Row],[Quantity]]*Table1[[#This Row],[Unit Price (NGN)]]) -> 8100000 | P8: =SUM(Table1[[#This Row],[Discount (%)]]*Table1[[#This Row],[Revenue]]) -> 1620000 | Q8: =SUM(Table1[[#This Row],[Revenue]]-Table1[[#This Row],[Discount Amount]]) -> 6480000
A9: ORD-96827 | B9: 45392 | C9: CUST-2069 | D9: Fatima Aliyu | E9: East | F9: Tablet Air | G9: Electronics | H9: =_xlfn.XLOOKUP(F9,Analysis!A:A,Analysis!B:B,) -> Electronics | I9: Online | J9: 11 | K9: 180000 | L9: 0 | M9: Completed | N9: =PROPER(M9) -> Completed | O9: =SUM(Table1[[#This Row],[Quantity]]*Table1[[#This Row],[Unit Price (NGN)]]) -> 1980000 | P9: =SUM(Table1[[#This Row],[Discount (%)]]*Table1[[#This Row],[Revenue]]) -> 0 | Q9: =SUM(Table1[[#This Row],[Revenue]]-Table1[[#This Row],[Discount Amount]]) -> 1980000
A10: ORD-52516 | B10: 45424 | C10: CUST-2535 | D10: Ibrahim Musa | E10: South | F10: Laptop Pro | G10: Electronics | H10: =_xlfn.XLOOKUP(F10,Analysis!A:A,Analysis!B:B,) -> Electronics | I10: In-Store | J10: 17 | K10: 450000 | L10: 0.05 | M10: Completed | N10: =PROPER(M10) -> Completed | O10: =SUM(Table1[[#This Row],[Quantity]]*Table1[[#This Row],[Unit Price (NGN)]]) -> 7650000 | P10: =SUM(Table1[[#This Row],[Discount (%)]]*Table1[[#This Row],[Revenue]]) -> 382500 | Q10: =SUM(Table1[[#This Row],[Revenue]]-Table1[[#This Row],[Discount Amount]]) -> 7267500
A11: ORD-99593 | B11: 45586 | C11: CUST-1700 | D11: Tunde Fashola | E11: South | F11: SmartPhone X | G11: Electronics | H11: =_xlfn.XLOOKUP(F11,Analysis!A:A,Analysis!B:B,) -> Electronics | I11: In-Store | J11: 6 | K11: 220000 | L11: 0.05 | M11: Completed | N11: =PROPER(M11) -> Completed | O11: =SUM(Table1[[#This Row],[Quantity]]*Table1[[#This Row],[Unit Price (NGN)]]) -> 1320000 | P11: =SUM(Table1[[#This Row],[Discount (%)]]*Table1[[#This Row],[Revenue]]) -> 66000 | Q11: =SUM(Table1[[#This Row],[Revenue]]-Table1[[#This Row],[Discount Amount]]) -> 1254000
A12: ORD-22240 | B12: 45606 | C12: CUST-1920 | D12: Ngozi Adeyemi | E12: South | F12: Wireless Earbuds | G12: Accessories | H12: =_xlfn.XLOOKUP(F12,Analysis!A:A,Analysis!B:B,) -> Accessories | I12: Online | J12: 2 | K12: 35000 | L12: 0 | M12: Completed | N12: =PROPER(M12) -> Completed | O12: =SUM(Table1[[#This Row],[Quantity]]*Table1[[#This Row],[Unit Price (NGN)]]) -> 70000 | P12: =SUM(Table1[[#This Row],[Discount (%)]]*Table1[[#This Row],[Revenue]]) -> 0 | Q12: =SUM(Table1[[#This Row],[Revenue]]-Table1[[#This Row],[Discount Amount]]) -> 70000
A13: ORD-68079 | B13: 45436 | C13: CUST-2707 | D13: Yemi Osinbajo | E13: South | F13: Monitor 4K | G13: Electronics | H13: =_xlfn.XLOOKUP(F13,Analysis!A:A,Analysis!B:B,) -> Electronics | I13: Online | J13: 7 | K13: 95000 | L13: 0.05 | M13: Pending | N13: =PROPER(M13) -> Pending | O13: =SUM(Table1[[#This Row],[Quantity]]*Table1[[#This Row],[Unit Price (NGN)]]) -> 665000 | P13: =SUM(Table1[[#This Row],[Discount (%)]]*Table1[[#This Row],[Revenue]]) -> 33250 | Q13: =SUM(Table1[[#This Row],[Revenue]]-Table1[[#This Row],[Discount Amount]]) -> 631750
A14: ORD-64505 | B14: 45529 | C14: CUST-3201 | D14: Ngozi Adeyemi | E14: East | F14: Webcam HD | G14: Accessories | H14: =_xlfn.XLOOKUP(F14,Analysis!A:A,Analysis!B:B,) -> Accessories | I14: In-Store | J14: 20 | K14: 22000 | L14: 0.2 | M14: Completed | N14: =PROPER(M14) -> Completed | O14: =SUM(Table1[[#This Row],[Quantity]]*Table1[[#This Row],[Unit Price (NGN)]]) -> 440000 | P14: =SUM(Table1[[#This Row],[Discount (%)]]*Table1[[#This Row],[Revenue]]) -> 88000 | Q14: =SUM(Table1[[#This Row],[Revenue]]-Table1[[#This Row],[Discount Amount]]) -> 352000
A15: ORD-66059 | B15: 45446 | C15: CUST-2641 | D15: Amaka Bello | E15: South | F15: Webcam HD | G15: Accessories | H15: =_xlfn.XLOOKUP(F15,Analysis!A:A,Analysis!B:B,) -> Accessories | I15: In-Store | J15: 16 | K15: 22000 | L15: 0 | M15: Pending | N15: =PROPER(M15) -> Pending | O15: =SUM(Table1[[#This Row],[Quantity]]*Table1[[#This Row],[Unit Price (NGN)]]) -> 352000 | P15: =SUM(Table1[[#This Row],[Discount (%)]]*Table1[[#This Row],[Revenue]]) -> 0 | Q15: =SUM(Table1[[#This Row],[Revenue]]-Table1[[#This Row],[Discount Amount]]) -> 352000
A16: ORD-99166 | B16: 45614 | C16: CUST-4075 | D16: Emeka Nwosu | E16: East | F16: SmartPhone X | G16: Electronics | H16: =_xlfn.XLOOKUP(F16,Analysis!A:A,Analysis!B:B,) -> Electronics | I16: Distributor | J16: 4 | K16: 220000 | L16: 0 | M16: Completed | N16: =PROPER(M16) -> Completed | O16: =SUM(Table1[[#This Row],[Quantity]]*Table1[[#This Row],[Unit Price (NGN)]]) -> 880000 | P16: =SUM(Table1[[#This Row],[Discount (%)]]*Table1[[#This Row],[Revenue]]) -> 0 | Q16: =SUM(Table1[[#This Row],[Revenue]]-Table1[[#This Row],[Discount Amount]]) -> 880000
A17: ORD-55193 | B17: 45648 | C17: CUST-3573 | D17: Amaka Bello | E17: East | F17: Wireless Earbuds | G17: Accessories | H17: =_xlfn.XLOOKUP(F17,Analysis!A:A,Analysis!B:B,) -> Accessories | I17: In-Store | J17: 11 | K17: 35000 | L17: 0 | M17: Completed | N17: =PROPER(M17) -> Completed | O17: =SUM(Table1[[#This Row],[Quantity]]*Table1[[#This Row],[Unit Price (NGN)]]) -> 385000 | P17: =SUM(Table1[[#This Row],[Discount (%)]]*Table1[[#This Row],[Revenue]]) -> 0 | Q17: =SUM(Table1[[#This Row],[Revenue]]-Table1[[#This Row],[Discount Amount]]) -> 385000
... A423: ORD-42725 | B423: 45637 | C423: CUST-4393 | D423: Ngozi Adeyemi | E423: East | F423: Tablet Air | G423: Electronics | H423: =_xlfn.XLOOKUP(F423,Analysis!A:A,Analysis!B:B,) -> Electronics | I423: Online | J423: 16 | K423: 180000 | L423: 0 | M423: Returned | N423: =PROPER(M423) -> Returned | O423: =SUM(Table1[[#This Row],[Quantity]]*Table1[[#This Row],[Unit Price (NGN)]]) -> 2880000 | P423: =SUM(Table1[[#This Row],[Discount (%)]]*Table1[[#This Row],[Revenue]]) -> 0 | Q423: =SUM(Table1[[#This Row],[Revenue]]-Table1[[#This Row],[Discount Amount]]) -> 2880000

Sheet Dashboard
A1: ACCESSORIES/ELECTRONICS SALES 2024
AC18: V

Sheet Analysis
A2: Product | B2: category | D2: Revenue by channel
A3: Laptop Pro | B3: Electronics | D3: Row Labels | E3: Sum of Net Revenue
A4: Keyboard Mech | B4: Accessories | D4: Distributor | E4: 133517100
A5: SmartPhone X | B5: Electronics | D5: In-Store | E5: 234164410
A6: Webcam HD | B6: Accessories | D6: Online | E6: 294607850
A7: Mouse Ergo | B7: Accessories | D7: Grand Total | E7: 662289360
A8: Monitor 4K | B8: Electronics
A9: Tablet Air | B9: Electronics | D9: Average unit price by region
A10: Wireless Earbuds | B10: Accessories | D10: Region | E10: Average unit price
D11: North | E11: =AVERAGEIF('Cleaned sheet'!E:E,D11,'Cleaned sheet'!K:K) -> 177152.55
A12: Average revenue by category | D12: South | E12: =AVERAGEIF('Cleaned sheet'!E:E,D12,'Cleaned sheet'!K:K) -> 190252.25
A13: Category | B13: Average unit price | D13: East | E13: =AVERAGEIF('Cleaned sheet'!E:E,D13,'Cleaned sheet'!K:K) -> 141015.62
A14: Accessories | B14: =AVERAGEIF('Cleaned sheet'!G:G,A14,'Cleaned sheet'!K:K) -> 25708.108 | D14: West | E14: =AVERAGEIF('Cleaned sheet'!E:E,D14,'Cleaned sheet'!K:K) -> 173285.71
A15: Electronics | B15: =AVERAGEIF('Cleaned sheet'!G:G,A15,'Cleaned sheet'!K:K) -> 279704.65
A19: KPI CARDS
A20: Total revenue | B20: Total orders | C20: AOV | D20: Return rate
A21: ='Pivot Tables'!B7 -> 662289360 | B21: ='Pivot Tables'!H11 -> 413 | C21: =SUM(A21/B21) -> 1603606.2 | D21: ='Pivot Tables'!I18 -> 0.10895884

Sheet TechBridge Sales 2024
A1: Order ID | B1: Order Date | C1: Customer ID | D1: Sales Rep | E1: Region | F1: Product | G1: Category | H1: Channel | I1: Quantity | J1: Unit Price (NGN) | K1: Discount (%) | L1: Status
A2: ORD-28465 | B2: 45566 | C2: CUST-4872 | D2: Ibrahim Musa | E2: East | F2: Smart Phone X | G2: Electronics | H2: In-Store | I2: 14 | J2: 220000 | K2: 0 | L2: Completed
A3: ORD-11553 | B3: 24/09/2024 | C3: CUST-2125 | E3: East | F3: Laptop Pro | G3: Electronics | H3: Online | I3: 17 | J3: 450000 | K3: 20 | L3: Completed
A4: ORD-71894 | B4: 18/08/2024 | C4: CUST-1592 | D4: Ibrahim Musa | E4: South | F4: Wireless Earbuds | G4: Accessories | I4: 17 | J4: 35000 | K4: 15 | L4: Completed
A5: ORD-25389 | B5: 20/06/2024 | C5: CUST-1904 | D5: Ngozi Adeyemi | E5: South | F5: Laptop pro | G5: electronics | H5: online | I5: 5 | J5: 450000 | K5: 5 | L5: Cancelled
A6: ORD-36111 | B6: 45390 | C6: CUST-1971 | D6: Ibrahim Musa | E6: North | F6: Keyboard Mech | G6: Accessories | H6: Distributor | I6: 19 | J6: 28000 | K6: 0 | L6: Returned
A7: ORD-44100 | B7: 13/01/2024 | C7: CUST-4500 | D7: Kemi Adebayo | E7: North | F7: Tablet Air | G7: Electronics | H7: In-Store | I7: 8 | J7: 180000 | K7: 0 | L7: Completed
A8: ORD-45509 | B8: 45509 | C8: CUST-1494 | D8: Ngozi Adeyemi | E8: East | F8: Laptop Pro | G8: Electronics | H8: Online | I8: 18 | J8: 450000 | K8: 20 | L8: Completed
A9: ORD-96827 | B9: 45569 | C9: CUST-2069 | D9: Fatima Aliyu | E9: East | F9: Tablet Air | G9: Electronics | H9: Online | I9: 11 | J9: 180000 | K9: 0 | L9: Completed
A10: ORD-52516 | B10: 45631 | C10: CUST-2535 | D10: Ibrahim Musa | E10: South | F10: Lap TopPro | G10: ELECTRONICS | H10: in store | I10: 17 | J10: 450000 | K10: 5 | L10: Completed
A11: ORD-99593 | B11: 21/10/2024 | C11: CUST-1700 | D11: Tunde Fashola | E11: South | F11: Smart Phone X | G11: Electronics | H11: In-Store | I11: 6 | J11: 220000 | K11: 5 | L11: Completed
A12: ORD-22240 | B12: 45576 | C12: CUST-1920 | D12: Ngozi Adeyemi | E12: South | F12: Wireless Earbuds | G12: Accessories | H12: Online | I12: 2 | J12: 35000 | K12: 0 | L12: Completed
A13: ORD-68079 | B13: 24/05/2024 | C13: CUST-2707 | D13: Yemi Osinbajo | E13: south | F13: Monitor 4K | G13: Electronics | H13: On-Line | I13: 7 | J13: 95000 | K13: 5 | L13: Pending
A14: ORD-64505 | B14: 25/08/2024 | C14: CUST-3201 | D14: Ngozi Adeyemi | E14: East | F14: Webcam HD | G14: Accessories | H14: In-Store | I14: 20 | J14: 22000 | K14: 20 | L14: Completed
A15: ORD-66059 | B15: 45357 | C15: CUST-2641 | D15: Amaka Bello | E15: South | F15: Webcam HD | G15: Accessories | H15: In-Store | I15: 16 | J15: 22000 | K15: 0 | L15: Pending
A16: ORD-99166 | B16: 18/11/2024 | C16: CUST-4075 | D16: Emeka Nwosu | E16: East | F16: Smart Phone X | G16: Electronics | H16: Distributor | I16: 4 | J16: 220000 | K16: 0 | L16: Completed
A17: ORD-55193 | B17: 22/12/2024 | C17: CUST-3573 | D17: Amaka Bello | E17: East | F17: Wireless Earbuds | G17: Accessories | H17: In-Store | I17: 11 | J17: 35000 | K17: 0 | L17: Completed
A18: ORD-26864 | B18: 45633 | C18: CUST-4255 | D18: Fatima Aliyu | E18: North | F18: Smart Phone X | G18: Electronics | H18: Distributor | I18: 5 | J18: 220000 | K18: 0 | L18: Completed
A19: ORD-50857 | B19: 21/11/2024 | C19: CUST-2529 | D19: Kemi Adebayo | E19: North | F19: Keyboard Mech | G19: Accessories | H19: Online | I19: 4 | J19: 28000 | K19: 0 | L19: Pending
A20: ORD-29198 | B20: 45566 | C20: CUST-4912 | D20: Amaka Bello | E20: East | F20: Laptop Pro | G20: Electronics | H20: Online | I20: 9 | J20: 450000 | K20: 15 | L20: Completed
A21: ORD-58629 | B21: 19/07/2024 | C21: CUST-4040 | D21: Chukwudi Eze | E21: West | F21: Webcam HD | G21: Accessories | H21: Online | I21: 16 | J21: 22000 | K21: 10 | L21: Completed
A22: ORD-51770 | B22: 21/12/2024 | C22: CUST-2373 | D22: Chukwudi Eze | E22: South | F22: Smart Phone X | G22: Electronics | H22: Online | I22: 10 | J22: 220000 | K22: 20 | L22: Completed
A23: ORD-57329 | B23: 13/03/2024 | C23: CUST-4525 | D23: Yemi Osinbajo | E23: West | F23: Monitor 4K | G23: Electronics | H23: Distributor | I23: 18 | J23: 95000 | K23: 15 | L23: Completed
A24: ORD-49467 | B24: 45393 | C24: CUST-3713 | D24: Tunde Fashola | E24: East | F24: Keyboard Mech | G24: Accessories | H24: In-Store | I24: 20 | J24: 28000 | K24: 15 | L24: Completed
A25: ORD-68515 | B25: 24/04/2024 | C25: CUST-1181 | D25: Ibrahim Musa | E25: West | F25: Laptop Pro | G25: Electronics | H25: In-Store | I25: 18 | J25: 450000 | K25: 0 | L25: Completed
A26: ORD-27987 | B26: 45601 | C26: CUST-1491 | D26: James Okafor | E26: West | F26: Laptop Pro | G26: Electronics | H26: Online | I26: 6 | J26: 450000 | K26: 0 | L26: Completed
A27: ORD-88504 | B27: 45299 | C27: CUST-1458 | D27: Fatima Aliyu | E27: East | F27: Monitor 4K | G27: Electronics | H27: Distributor | I27: 8 | J27: 95000 | K27: 0 | L27: Pending
A28: ORD-21919 | B28: 26/08/2024 | C28: CUST-1227 | D28: Kemi Adebayo | E28: South | F28: Webcam HD | G28: Accessories | H28: In-Store | I28: 14 | J28: 999999999 | K28: 5 | L28: Completed
A29: ORD-23357 | B29: 45293 | C29: CUST-1252 | D29: Ngozi Adeyemi | E29: South | F29: Tablet Air | G29: Electronics | H29: In-Store | I29: 13 | J29: 180000 | K29: 0 | L29: Completed
A30: ORD-92288 | B30: 15/07/2024 | C30: CUST-1309 | D30: Amaka Bello | E30: West | F30: Keyboard Mech | G30: Accessories | H30: In-Store | I30: 9 | J30: 28000 | K30: 15 | L30: Cancelled
A31: ORD-87820 | B31: 27/09/2024 | C31: CUST-3087 | D31: Tunde Fashola | E31: West | F31: Monitor 4K | G31: Electronics | H31: In-Store | I31: 10 | J31: 95000 | K31: 5 | L31: Completed
A32: ORD-20592 | B32: 21/06/2024 | C32: CUST-1724 | D32: Fatima Aliyu | E32: South | F32: Mouse Ergo | G32: Accessories | H32: Online | I32: 1 | J32: 18000 | K32: 5 | L32: Returned
A33: ORD-92050 | B33: 16/09/2024 | C33: CUST-1192 | D33: Fatima Aliyu | E33: South | F33: Keyboard Mech | G33: Accessories | H33: Online | I33: 17 | J33: 28000 | K33: 0 | L33: Completed
A34: ORD-21506 | B34: 45637 | C34: n | D34: Amaka Bello | E34: North | F34: Monitor 4K | G34: Electronics | H34: In-Store | I34: 10 | J34: 1 | K34: 0 | L34: Completed
A35: ORD-21970 | B35: 27/11/2024 | C35: CUST-4524 | D35: Yemi Osinbajo | E35: North | F35: Wireless Earbuds | G35: Accessories | H35: Online | I35: 9 | J35: 35000 | K35: 10 | L35: Completed
A36: ORD-28367 | B36: 45509 | C36: CUST-4341 | D36: Yemi Osinbajo | E36: East | F36: Webcam HD | G36: Accessories | H36: In-Store | I36: 20 | J36: 22000 | K36: 20 | L36: Cancelled
A37: ORD-76648 | B37: 45627 | C37: CUST-2265 | D37: Chukwudi Eze | E37: South | F37: Monitor 4K | G37: Electronics | H37: Distributor | I37: 16 | J37: 95000 | K37: 0 | L37: Pending
A38: ORD-91006 | B38: 13/10/2024 | C38: CUST-1631 | D38: Chukwudi Eze | E38: South | F38: Tablet Air | G38: Electronics | H38: In-Store | I38: 6 | J38: 180000 | K38: 15 | L38: Completed
A39: ORD-26059 | B39: 45330 | C39: CUST-1688 | D39: Yemi Osinbajo | E39: West | F39: Laptop Pro | G39: Electronics | H39: Online | I39: 16 | J39: 450000 | K39: 0 | L39: Completed
A40: ORD-16839 | B40: 18/06/2024 | C40: CUST-4826 | D40: Amaka Bello | E40: South | F40: Mouse Ergo | G40: Accessories | H40: In-Store | I40: 4 | J40: 18000 | K40: 0 | L40: Completed
A41: ORD-17355 | B41: 45455 | C41: CUST-1338 | D41: Kemi Adebayo | E41: East | F41: Laptop Pro | G41: Electronics | H41: Online | I41: 11 | J41: 450000 | K41: 10 | L41: Completed
A42: ORD-26406 | B42: 18/10/2024 | C42: CUST-1382 | D42: Tunde Fashola | E42: South | F42: Laptop Pro | G42: Electronics | H42: In-Store | I42: 19 | J42: 450000 | K42: 10 | L42: Completed
A43: ORD-50250 | B43: 45632 | C43: CUST-2067 | D43: Yemi Osinbajo | E43: East | F43: Keyboard Mech | G43: Accessories | H43: Online | I43: 4 | J43: 28000 | K43: 5 | L43: Completed
A44: ORD-31473 | B44: 17/06/2024 | C44: CUST-3118 | D44: Emeka Nwosu | E44: South | F44: Mouse Ergo | G44: Accessories | H44: Distributor | I44: 5 | J44: 18000 | K44: 15 | L44: Returned
A45: ORD-65027 | B45: 45384 | C45: CUST-4427 | D45: Kemi Adebayo | E45: North | F45: Mouse Ergo | G45: Accessories | H45: In-Store | I45: 1 | J45: 18000 | K45: 15 | L45: Pending
A46: ORD-33969 | B46: 13/07/2024 | C46: CUST-4941 | D46: Kemi Adebayo | E46: East | F46: Smart Phone X | G46: Electronics | H46: Online | I46: 16 | J46: 220000 | K46: 20 | L46: Completed
A47: ORD-15943 | B47: 16/05/2024 | C47: CUST-1475 | D47: Amaka Bello | E47: south | F47: Lap TopPro | G47: ELECTRONICS | H47: Instore | I47: 5 | J47: 450000 | K47: 5 | L47: completed
A48: ORD-54284 | B48: 45540 | C48: CUST-4452 | D48: Kemi Adebayo | E48: East | F48: Lap TopPro | G48: electronics | H48: ONLINE | I48: 8 | J48: 450000 | K48: 0 | L48: Returned
A49: ORD-26728 | B49: 13/01/2024 | C49: CUST-3424 | D49: Yemi Osinbajo | E49: South | F49: Webcam HD | G49: Accessories | H49: Online | I49: 3 | J49: 22000 | K49: 15 | L49: Completed
A50: ORD-52600 | B50: 45481 | C50: CUST-2453 | D50: Emeka Nwosu | E50: East | F50: Tablet Air | G50: Electronics | H50: Distributor | I50: 20 | J50: 180000 | K50: 15 | L50: Returned
A51: ORD-70689 | B51: 14/09/2024 | C51: CUST-4964 | D51: Ibrahim Musa | E51: North | F51: Laptop Pro | G51: Electronics | H51: In-Store | I51: 5 | J51: 450000 | K51: 5 | L51: Pending
A52: ORD-76132 | B52: 45505 | C52: CUST-3898 | D52: Kemi Adebayo | E52: West | F52: Tablet Air | G52: Electronics | H52: In-Store | I52: 17 | J52: 180000 | K52: 10 | L52: Completed
A53: ORD-63368 | B53: 28/09/2024 | C53: CUST-2531 | D53: James Okafor | E53: North | F53: Mouse Ergo | G53: Accessories | H53: In-Store | I53: 3 | J53: 18000 | K53: 0 | L53: Completed
A54: ORD-72402 | B54: 26/08/2024 | C54: CUST-1070 | D54: Amaka Bello | E54: East | F54: Mouse Ergo | G54: Accessories | H54: In-Store | I54: 13 | J54: 18000 | K54: 15 | L54: Pending
A55: ORD-31992 | B55: 45568 | C55: CUST-1442 | D55: Yemi Osinbajo | E55: North | F55: Smart Phone X | G55: Electronics | H55: Distributor | I55: 19 | J55: 220000 | K55: 15 | L55: Completed
A56: ORD-91183 | B56: 22/07/2024 | C56: CUST-3390 | D56: Yemi Osinbajo | E56: North | F56: Smart Phone X | G56: Electronics | H56: Distributor | I56: 9 | J56: 220000 | K56: 0 | L56: Cancelled
A57: ORD-15482 | B57: 26/06/2024 | C57: CUST-4982 | D57: James Okafor | E57: East | F57: Laptop Pro | G57: Electronics | H57: In-Store | I57: 8 | J57: 450000 | K57: 15 | L57: Completed
A58: ORD-28327 | B58: 21/05/2024 | C58: CUST-1345 | D58: Ngozi Adeyemi | E58: North | F58: Wireless Earbuds | G58: Accessories | H58: In-Store | I58: 20 | J58: 35000 | K58: 15 | L58: Returned
A59: ORD-50577 | B59: 21/07/2024 | C59: CUST-4242 | D59: Fatima Aliyu | E59: East | F59: Webcam HD | G59: accessories | H59: in-store | I59: 17 | J59: 22000 | K59: 0 | L59: completed
A60: ORD-21164 | B60: 18/02/2024 | C60: CUST-4131 | D60: Ibrahim Musa | E60: North | F60: Wireless Earbuds | G60: Accessories | H60: In-Store | I60: 20 | J60: 35000 | K60: 0 | L60: Completed
A61: ORD-73277 | B61: 14/05/2024 | C61: CUST-4770 | D61: Amaka Bello | E61: North | F61: Smart Phone X | G61: Electronics | H61: In-Store | I61: 12 | J61: 220000 | K61: 0 | L61: Cancelled
A62: ORD-54922 | B62: 25/06/2024 | C62: CUST-1771 | D62: Chukwudi Eze | E62: East | F62: Mouse Ergo | G62: Accessories | H62: Online | I62: 1 | J62: 18000 | K62: 0 | L62: Pending
A63: ORD-64896 | B63: 24/09/2024 | C63: CUST-3530 | D63: Amaka Bello | E63: East | F63: Smart Phone X | G63: Electronics | H63: Online | I63: 4 | J63: 220000 | K63: 5 | L63: Pending
A64: ORD-78614 | B64: 17/02/2024 | C64: CUST-3228 | D64: Tunde Fashola | E64: East | F64: Monitor 4K | G64: Electronics | H64: In-Store | I64: 18 | J64: 95000 | K64: 0 | L64: Completed
A65: ORD-25765 | B65: 45446 | C65: CUST-4981 | D65: Ngozi Adeyemi | E65: East | F65: Mouse Ergo | G65: Accessories | H65: In-Store | I65: 5 | J65: 18000 | K65: 0 | L65: Completed
A66: ORD-39657 | B66: 45417 | C66: CUST-1420 | D66: Ibrahim Musa | E66: North | F66: Monitor 4K | G66: Electronics | H66: In-Store | I66: 10 | J66: 95000 | K66: 0 | L66: Completed
A67: ORD-11217 | B67: 46297 | C67: CUST-4346 | D67: Amaka Bello | E67: East | F67: Laptop Pro | G67: Electronics | H67: Online | I67: 5 | J67: 450000 | K67: 5 | L67: Completed
A68: ORD-52981 | B68: 15/05/2024 | C68: CUST-3468 | D68: Ibrahim Musa | E68: South | F68: Laptop Pro | G68: Electronics | H68: Online | I68: 12 | J68: 450000 | K68: 5 | L68: Completed
A69: ORD-97797 | B69: 17/09/2024 | C69: CUST-3819 | D69: Yemi Osinbajo | E69: North | F69: Monitor 4K | G69: Electronics | H69: Online | I69: 8 | J69: 95000 | K69: 5 | L69: Cancelled
A70: ORD-52917 | B70: 25/04/2024 | C70: CUST-1652 | D70: Kemi Adebayo | E70: North | F70: Monitor 4K | G70: Electronics | H70: Online | I70: 16 | J70: 95000 | K70: 0 | L70: Completed
A71: ORD-30289 | B71: 45478 | C71: CUST-4967 | D71: James Okafor | E71: North | F71: Wireless Earbuds | G71: Accessories | H71: In-Store | I71: 2 | J71: 35000 | K71: 15 | L71: Cancelled
A72: ORD-16755 | B72: 22/07/2024 | C72: CUST-3477 | D72: Yemi Osinbajo | E72: North | F72: Laptop Pro | G72: Electronics | H72: Online | I72: 7 | J72: 450000 | K72: 20 | L72: Pending
A73: ORD-45382 | B73: 22/04/2024 | C73: CUST-2328 | D73: James Okafor | E73: South | F73: Webcam HD | G73: Accessories | H73: Online | I73: 11 | J73: 22000 | K73: 5 | L73: Returned
A74: ORD-33496 | B74: 17/02/2024 | C74: CUST-1609 | D74: Ngozi Adeyemi | E74: South | F74: Smart Phone X | G74: Electronics | H74: In-Store | I74: 17 | J74: 220000 | K74: 0 | L74: Cancelled
A75: ORD-29369 | B75: 19/01/2024 | C75: CUST-4883 | D75: Amaka Bello | E75: South | F75: Wireless Earbuds | G75: Accessories | H75: Online | I75: 15 | J75: 35000 | K75: 0 | L75: Completed
A76: ORD-39389 | B76: 45333 | C76: CUST-4089 | D76: James Okafor | E76: SOUTH | F76: Smart Phone X | G76: Electronics | H76: in-store | I76: 1 | J76: 220000 | K76: 10 | L76: Completed
A77: ORD-45645 | B77: 45475 | C77: CUST-1557 | D77: Yemi Osinbajo | E77: North | F77: Wireless Earbuds | G77: Accessories | H77: In-Store | I77: 4 | J77: 35000 | K77: 0 | L77: Completed
A78: ORD-15083 | B78: 23/06/2024 | C78: CUST-1973 | D78: James Okafor | E78: South | F78: Keyboard Mech | G78: Accessories | H78: Online | I78: 9 | J78: 28000 | K78: 0 | L78: Completed
A79: ORD-63511 | B79: 13/05/2024 | C79: CUST-1753 | D79: Tunde Fashola | E79: West | F79: Tablet Air | G79: Electronics | H79: In-Store | I79: 8 | J79: 180000 | K79: 0 | L79: Completed
A80: ORD-76469 | B80: 14/11/2024 | C80: CUST-2336 | D80: Ibrahim Musa | E80: South | F80: Laptop Pro | G80: Electronics | H80: Distributor | I80: 18 | J80: 450000 | K80: 0 | L80: Pending
A81: ORD-10350 | B81: 23/08/2024 | C81: CUST-3432 | D81: Kemi Adebayo | E81: East | F81: Keyboard Mech | G81: Accessories | H81: Online | I81: 8 | J81: 28000 | K81: 0 | L81: Returned
A82: ORD-23238 | B82: 15/05/2024 | C82: CUST-3603 | D82: Fatima Aliyu | E82: South | F82: Keyboard Mech | G82: Accessories | H82: Distributor | I82: 12 | J82: 28000 | K82: 0 | L82: Returned
A83: ORD-13445 | B83: 19/09/2024 | C83: CUST-2511 | D83: Kemi Adebayo | E83: EAST | F83: Monitor 4K | G83: Electronics | H83: in store | I83: 5 | J83: 95000 | K83: 10 | L83: COMPLETED
A84: ORD-28818 | B84: 45298 | C84: CUST-3518 | D84: Fatima Aliyu | E84: south | F84: Laptop pro | G84: Electronics | H84: Instore | I84: 14 | J84: 450000 | K84: 0 | L84: COMPLETED
A85: ORD-75546 | B85: 45323 | C85: CUST-1561 | D85: Fatima Aliyu | E85: East | F85: Laptop Pro | G85: Electronics | H85: Online | I85: 17 | J85: 450000 | K85: 5 | L85: Completed
A86: ORD-99282 | B86: 45630 | C86: CUST-3002 | D86: Yemi Osinbajo | E86: West | F86: Laptop Pro | G86: Electronics | H86: In-Store | I86: 16 | J86: 450000 | K86: 10 | L86: Cancelled
A87: ORD-85066 | B87: 45573 | C87: CUST-1323 | D87: Ibrahim Musa | E87: East | F87: Wireless Earbuds | G87: Accessories | H87: online | I87: 17 | J87: 35000 | K87: 10 | L87: Completed
A88: ORD-64381 | B88: 17/07/2024 | C88: CUST-2531 | D88: Ngozi Adeyemi | E88: West | F88: Laptop Pro | G88: Electronics | H88: Online | I88: 12 | J88: 450000 | K88: 0 | L88: Completed
A89: ORD-99192 | B89: 45361 | C89: CUST-2576 | D89: Ibrahim Musa | E89: North | F89: Keyboard Mech | G89: ACCESSORIES | H89: ONLINE | I89: 17 | J89: 28000 | L89: Completed
A90: ORD-43438 | B90: 22/10/2024 | C90: CUST-3960 | D90: Amaka Bello | E90: South | F90: Smart Phone X | G90: Electronics | H90: In-Store | I90: 1 | J90: 220000 | K90: 0 | L90: Completed
A91: ORD-90301 | B91: 27/07/2024 | C91: CUST-4714 | D91: Tunde Fashola | E91: West | F91: Webcam HD | G91: Accessories | H91: In-Store | I91: 16 | J91: 22000 | K91: 5 | L91: Returned
A92: ORD-17492 | B92: 16/10/2024 | C92: CUST-3059 | D92: Tunde Fashola | E92: South | F92: Laptop Pro | G92: Electronics | H92: Online | I92: 17 | J92: 450000 | K92: 0 | L92: Completed
A93: ORD-86326 | B93: 45293 | C93: CUST-1264 | D93: Ngozi Adeyemi | E93: South | F93: Laptop Pro | G93: Electronics | H93: Online | I93: 5 | J93: 450000 | K93: 0 | L93: Cancelled
A94: ORD-20084 | B94: 19/03/2024 | C94: CUST-1984 | D94: Yemi Osinbajo | E94: East | F94: Laptop Pro | G94: Electronics | H94: Online | I94: 18 | J94: 450000 | K94: 0 | L94: Completed
A95: ORD-38124 | B95: 16/12/2024 | C95: CUST-1819 | D95: Amaka Bello | E95: South | F95: Laptop Pro | G95: Electronics | H95: Online | I95: 15 | J95: 450000 | K95: 0 | L95: Completed
A96: ORD-83242 | B96: 26/11/2024 | C96: CUST-2262 | D96: James Okafor | E96: West | F96: Mouse Ergo | G96: Accessories | H96: Distributor | I96: 1 | J96: 18000 | K96: 15 | L96: Pending
A97: ORD-23845 | B97: 28/05/2024 | C97: CUST-3193 | D97: Fatima Aliyu | E97: West | F97: Smart Phone X | G97: Electronics | H97: Distributor | I97: 13 | J97: 220000 | K97: 15 | L97: Completed
A98: ORD-81376 | B98: 45423 | C98: CUST-4720 | D98: Emeka Nwosu | E98: East | F98: Wireless Earbuds | G98: Accessories | H98: In-Store | I98: 3 | J98: 35000 | K98: 0 | L98: Completed
A99: ORD-96511 | B99: 45603 | C99: CUST-2141 | D99: Amaka Bello | E99: East | F99: Wireless Earbuds | G99: Accessories | H99: Distributor | I99: 12 | J99: 35000 | K99: 15 | L99: Completed
A100: ORD-90728 | B100: 15/08/2024 | C100: CUST-2784 | D100: Yemi Osinbajo | E100: East | F100: Webcam HD | G100: Accessories | H100: Distributor | I100: 8 | J100: 22000 | K100: 20 | L100: Completed
...

Sheet Pivot Tables
A1: Sales rep revenue by region | D1: Revenue by sales rep | G1: Quantity & average unit price by product | L1: Revenue by product
A2: Row Labels | B2: Sum of Net Revenue | D2: Row Labels | E2: Sum of Net Revenue | G2: Row Labels | H2: Count of Order ID | I2: Sum of Quantity | J2: Average of Unit Price (NGN) | L2: Row Labels | M2: Sum of Net Revenue
A3: South | B3: 213065150 | D3: Ibrahim Musa | E3: 111935250 | G3: Laptop Pro | H3: 95 | I3: 967 | J3: 445315.79 | L3: Laptop Pro | M3: 403657500
A4: East | B4: 175019550 | D4: Fatima Aliyu | E4: 77621150 | G4: SmartPhone X | H4: 54 | I4: 491 | J4: 220000 | L4: SmartPhone X | M4: 102564000
A5: North | B5: 174104510 | D5: Tunde Fashola | E5: 75246500 | G5: Tablet Air | H5: 40 | I5: 437 | J5: 180000 | L5: Tablet Air | M5: 72756000
A6: West | B6: 100100150 | D6: Yemi Osinbajo | E6: 74782550 | G6: Monitor 4K | H6: 44 | I6: 445 | J6: 92840.932 | L6: Monitor 4K | M6: 39292010
A7: Grand Total | B7: 662289360 | D7: Ngozi Adeyemi | E7: 68802300 | G7: Wireless Earbuds | H7: 40 | I7: 444 | J7: 35000 | L7: Wireless Earbuds | M7: 14246750
D8: Grand Total | E8: 408387750 | G8: Keyboard Mech | H8: 52 | I8: 546 | J8: 28000 | L8: Keyboard Mech | M8: 14236600
A9: Row Labels | B9: Sum of Net Revenue | G9: Webcam HD | H9: 42 | I9: 460 | J9: 22000 | L9: Webcam HD | M9: 9166300
A10: Jan | B10: 42681950 | G10: Mouse Ergo | H10: 46 | I10: 397 | J10: 18000 | L10: Mouse Ergo | M10: 6370200
A11: Feb | B11: 36854500 | G11: Grand Total | H11: 413 | I11: 4187 | J11: 169680.39 | L11: Grand Total | M11: 662289360
A12: Mar | B12: 81983300
A13: Apr | B13: 65072400 | G13: Status count
A14: May | B14: 68612050 | G14: Row Labels | H14: Count of Order ID | I14: % of Total Orders | K14: Monthly revenue trend by channel
A15: Jun | B15: 46005700 | G15: Completed | H15: 265 | I15: 0.64164649 | K15: Sum of Net Revenue | L15: Column Labels
A16: Jul | B16: 84185650 | G16: Pending | H16: 56 | I16: 0.13559322 | K16: Row Labels | L16: Distributor | M16: In-Store | N16: Online | O16: Grand Total
A17: Aug | B17: 55602950 | D17: Unit sold by channel | G17: Cancelled | H17: 47 | I17: 0.11380145 | K17: Jan | L17: 3071100 | M17: 15828000 | N17: 23782850 | O17: 42681950
A18: Sep | B18: 40103500 | D18: Row Labels | E18: Sum of Quantity | G18: Returned | H18: 45 | I18: 0.10895884 | K18: Feb | L18: 2511200 | M18: 28665500 | N18: 3540300 | O18: 34717000
A19: Oct | B19: 66571050 | D19: Distributor | E19: 849 | G19: Grand Total | H19: 413 | I19: 1 | K19: Mar | L19: 35443950 | M19: 7565350 | N19: 38974000 | O19: 81983300
A20: Nov | B20: 39991710 | D20: In-Store | E20: 1652 | K20: Apr | L20: 13703400 | M20: 38762900 | N20: 12156100 | O20: 64622400
A21: Dec | B21: 34624600 | D21: Online | E21: 1686 | K21: May | L21: 8656500 | M21: 25860400 | N21: 31701150 | O21: 66218050
A22: Grand Total | B22: 662289360 | D22: Grand Total | E22: 4187 | G22: Revenue by category | K22: Jun | L22: 3519000 | M22: 14135200 | N22: 27847500 | O22: 45501700
G23: Row Labels | H23: Sum of Net Revenue | K23: Jul | L23: 18915350 | M23: 23814900 | N23: 41455400 | O23: 84185650
G24: Electronics | H24: 618269510 | K24: Aug | L24: 12545300 | M24: 12652150 | N24: 30405500 | O24: 55602950
G25: Accessories | H25: 44019850 | K25: Sep | L25: 4011500 | M25: 16778800 | N25: 19313200 | O25: 40103500
G26: Grand Total | H26: 662289360 | K26: Oct | L26: 17473500 | M26: 27884600 | N26: 21212950 | O26: 66571050
K27: Nov | L27: 10450800 | M27: 8544010 | N27: 20996900 | O27: 39991710
K28: Dec | L28: 821500 | M28: 13168600 | N28: 20634500 | O28: 34624600
K29: Grand Total | L29: 131123100 | M29: 233660410 | N29: 292020350 | O29: 656803860
